{"type":"FeatureCollection","features":[
{"geometry": {"type": "Point", "coordinates": [-78.480606, 38.0254035]}, "type": "Feature", "properties": {"Access": " ", "Safety": " ", "DryBoard": "car road [drawing of car]", "Events": " ", "Buildings": " ", "Nature": " ", "Food": " ", "POINT_X": -78.48060597, "POINT_Y": 38.02540354, "History": " ", "ATT_NAME": "Photo1.jpg", "Developmen": " ", "Sound": " ", "OBJECTID": 1, "tags": "Transportation", "ImageURL": "http://pollocksbranch.virginia.edu/sites/pollocksbranch.virginia.edu/files/workshopparticipantphotos/ATT24_Photo1.jpg", "Play": " ", "Experience": " ", "Future": " ", "Place": " ", "Transporta": "Transportation", "SacredSpac": " ", "Gardens": " ", "MysteryWon": " ", "Comment": " ", "Art": " ", "Family": " ", "Environmen": " ", "ATTACHMENT": 24, "Home": " "}}
]}