{"type":"FeatureCollection","features":[
{"geometry": {"type": "Point", "coordinates": [-78.4823281, 38.0256406]}, "type": "Feature", "properties": {"Access": " ", "Safety": " ", "DryBoard": "market", "Events": "Events", "Buildings": " ", "Nature": " ", "Food": " ", "POINT_X": -78.48232811, "POINT_Y": 38.02564062, "History": " ", "ATT_NAME": "Photo1.jpg", "Developmen": " ", "Sound": " ", "OBJECTID": 1, "tags": "Events", "ImageURL": "http://pollocksbranch.virginia.edu/sites/pollocksbranch.virginia.edu/files/workshopparticipantphotos/ATT41_Photo1.jpg", "Play": " ", "Experience": " ", "Future": " ", "Place": " ", "Transporta": " ", "SacredSpac": " ", "Gardens": " ", "MysteryWon": " ", "Comment": " ", "Art": " ", "Family": " ", "Environmen": " ", "ATTACHMENT": 41, "Home": " "}}
]}