{"type":"FeatureCollection","features":[
{"geometry": {"type": "Point", "coordinates": [-79.1938651, 37.3304425]}, "type": "Feature", "properties": {"Name": "Lynchburg Regional Airport", "OBJECTID": 54, "Creator": "CONWASC", "DateModify": 1427914937000, "DateCreated": 1427914904000, "Link": "http://www.lynchburgva.gov/airport", "Editor": "CONWASC", "Address": "350 TERMINAL DR", "Type": "Other"}}
]}