{"type":"FeatureCollection","features":[
{"geometry": {"type": "Point", "coordinates": [-79.1867966, 37.3825273]}, "type": "Feature", "properties": {"Owner1": "BAYS, CONRAD D", "City": "LYNCHBURG", "RecordNo": "ZON17-00297", "MailingAddress": "4824 WINDSOR AVE", "CensusTract": "10", "MailingZipCode": "24502-1533", "MailingState": "VA", "ConcatenatedAddress": "4824 WINDSOR AVE", "Status": "VERBAL WARNING", "eTRAKitURL": "http://etrakit.lynchburgva.gov/etrakit3/Search/parcel.aspx?activityNo=DTF_00879651", "Remarks": "", "CompletedDate": null, "OBJECTID": 185557, "ScheduledDate": 1511740800000, "MailingCity": "LYNCHBURG", "Notes": null, "CompletedTime": null, "LastChangedDate": 1511928480000, "GroupName": "VIOLATION", "HouseNumberSuffix": "", "RecordID": "KTH:1711150802321847", "ScheduledTime": "10:00 AM", "ParcelID": "05503008", "ZipCode": 24502, "InspectionType": "Zoning Followup Insp", "UnitNumber": "", "Result": null, "Duration": null, "Inspector": "KTH", "HouseNumber": "4824", "StreetName": "WINDSOR AVE"}},
{"geometry": {"type": "Point", "coordinates": [-79.2315369, 37.3437487]}, "type": "Feature", "properties": {"Owner1": "JOHNSON, DAVID L II & JASMINE", "City": "LYNCHBURG", "RecordNo": "ZON17-00303", "MailingAddress": "105 FREDERICK DR", "CensusTract": "16", "MailingZipCode": "24502-2715", "MailingState": "VA", "ConcatenatedAddress": "105 FREDERICK DR", "Status": "AWAITING INSPECTION", "eTRAKitURL": "http://etrakit.lynchburgva.gov/etrakit3/Search/parcel.aspx?activityNo=DTF_00890872", "Remarks": "", "CompletedDate": null, "OBJECTID": 185567, "ScheduledDate": 1511913600000, "MailingCity": "LYNCHBURG", "Notes": null, "CompletedTime": null, "LastChangedDate": 1511928480000, "GroupName": "VIOLATION", "HouseNumberSuffix": "", "RecordID": "KTH:1711280328008105", "ScheduledTime": "9:30 AM", "ParcelID": "26314012", "ZipCode": 24502, "InspectionType": "Zoning Initial Insp", "UnitNumber": "", "Result": null, "Duration": null, "Inspector": "KTH", "HouseNumber": "105", "StreetName": "FREDERICK DR"}}
]}