{"type":"FeatureCollection","features":[
{"geometry": {"type": "Point", "coordinates": [-77.273083, 38.84777]}, "type": "Feature", "properties": {"id_name": "VAD093952935_Motiva Enterprises LLC-Fairfax Terminal (Star Enterprise-Picket Rd)", "FolderPath": "Motiva Enterprises, LLC - Fairfax Terminal", "Name": "Motiva Enterprises, LLC - Fairfax Terminal", "LabelID": 0, "OID": 1, "SymbolID": 0, "Snippet": "", "Base": 0, "PopupInfo": "<b>Motiva Enterprises, LLC - Fairfax Terminal</b><br><p>3800 Pickett Rd<br>Fairfax VA 22031<br><p>EPA ID #: VAD093952935<br><p>", "HasLabel": -1, "AltMode": -1, "epa_id": "VAD093952935"}}
]}