{"type":"FeatureCollection","features":[
{"geometry": {"type": "Point", "coordinates": [-76.288634, 36.767527]}, "type": "Feature", "properties": {"id_name": "VAD000737346_Safety-Kleen systems, Inc. Chesapeake Service Center", "FolderPath": "Safety-Kleen Systems, Incorporated - Chesapeake", "Name": "Safety-Kleen Systems, Incorporated - Chesapeake", "LabelID": 0, "OID": 1, "SymbolID": 1, "Snippet": "", "Base": 0, "PopupInfo": "<b>Safety-Kleen Systems, Incorporated - Chesapeake</b><br><p>4545 Bainbridge Boulevard<br>Chesapeake, VA  23320<br><p>EPA ID #: VAD000737346<br><p>", "HasLabel": -1, "AltMode": -1, "epa_id": "VAD000737346"}}
]}