{"type":"FeatureCollection","features":[
{"geometry": {"type": "Point", "coordinates": [-76.6232739, 37.27514]}, "type": "Feature", "properties": {"id_name": "VAD988193223_Virginia Emer. Fuel Storage Fac.", "FolderPath": "Virginia Emergency Fuel Storage Facility", "Name": "Virginia Emergency Fuel Storage Facility", "LabelID": 0, "OID": 1, "SymbolID": 0, "Snippet": "", "Base": 0, "PopupInfo": "<b>Virginia Emergency Fuel Storage Facility</b><br><p>Junction VA Rts 641 & 199<br>Yorktown VA 23690<br><p>EPA ID #: VAD988193223<br><p>", "HasLabel": -1, "AltMode": -1, "epa_id": "VAD988193223"}}
]}