{"type":"FeatureCollection","features":[
{"geometry": {"type": "Point", "coordinates": [-77.2728339, 37.2984035]}, "type": "Feature", "properties": {"id_name": "VAD065385296_Honeywell International, Inc. - Hopewell (Allied Signal)", "FolderPath": "Honeywell International, Incorporated", "Name": "Honeywell International, Incorporated", "LabelID": 0, "OID": 1, "SymbolID": 0, "Snippet": "", "Base": 0, "PopupInfo": "<b>Honeywell International, Incorporated</b><br><p>906 E Randolph Rd.<br>Hopewell VA 23860<br><p>EPA ID #: VAD065385296<br><p>", "HasLabel": -1, "AltMode": -1, "epa_id": "VAD065385296"}}
]}