{"type":"FeatureCollection","features":[
{"geometry": {"type": "Point", "coordinates": [-80.4187605, 37.2158853]}, "type": "Feature", "properties": {"id_name": "VAD074747908_Virginia Tech", "FolderPath": "Temporary Places/Virginia Tech.kml", "Name": "Virginia Tech", "LabelID": 0, "OID": 1, "SymbolID": 0, "Snippet": "", "Base": 0, "PopupInfo": "<b>Virginia Tech</b><br><p>459 Tech Center Dr<br>Blacksburg VA 24061<br><p>EPA ID #: VAD074747908<br><p>", "HasLabel": -1, "AltMode": -1, "epa_id": "VAD074747908"}}
]}