{"type":"FeatureCollection","features":[
{"geometry": {"type": "Point", "coordinates": [-78.4581135, 38.1358229]}, "type": "Feature", "properties": {"id_name": "VAD089027759_Avionics Specialties Inc", "FolderPath": "Avionics Specialties, Incorporated", "Name": "Avionics Specialties, Incorporated", "LabelID": 0, "OID": 1, "SymbolID": 1, "Snippet": "", "Base": 0, "PopupInfo": "<b>Avionics Specialties, Incorporated</b><br><p>3367 Earlysville Rd<br>Earlysville VA 22936<br><p>EPA ID #  VAD089027759<br><p>", "HasLabel": -1, "AltMode": -1, "epa_id": "VAD089027759"}}
]}