{"type":"FeatureCollection","features":[
{"geometry": {"type": "Point", "coordinates": [-78.1751159, 39.1575299]}, "type": "Feature", "properties": {"FolderPath": "Federal Mogul", "Name": "Federal Mogul", "LabelID": 0, "OID": 1, "SymbolID": 0, "Snippet": "", "Base": 0, "PopupInfo": "<b>Federal Mogul</b><p>2410 Papermill Rd<br>Winchester VA 22601<br><p>EPA ID #:  VAD003070976<br><p>", "HasLabel": -1, "AltMode": -1}}
]}