{"type":"FeatureCollection","features":[
{"geometry": {"type": "Point", "coordinates": [-76.307669, 36.811797]}, "type": "Feature", "properties": {"id_name": "VAD003174810_Procter & Gamble Mfg. Co.", "FolderPath": "Procter and Gamble Manufacturing Company", "Name": "Procter and Gamble Manufacturing Company", "LabelID": 0, "OID": 1, "SymbolID": 0, "Snippet": "", "Base": 0, "PopupInfo": "<b>Procter and Gamble Manufacturing Company</b><br><p>3600 Elm Ave<br>Portsmouth VA 23704<br><p>EPA ID #:VAD003174810<br><p>", "HasLabel": -1, "AltMode": -1, "epa_id": "VAD003174810"}}
]}