{"type":"FeatureCollection","features":[
{"geometry": {"type": "Point", "coordinates": [-79.0580214, 37.4021669]}, "type": "Feature", "properties": {"id_name": "VAD000820506_Intermet Archer Creek Foundry", "FolderPath": "Archer Creek Foundry", "Name": "Archer Creek Foundry", "LabelID": 0, "OID": 1, "SymbolID": 0, "Snippet": "", "Base": 0, "PopupInfo": "<b>Archer Creek Foundry</b><br><p>1132 Mount Athos Rd<br>Lynchburg VA 24504<br><p>EPA ID #: VAD000820506<br><p>", "HasLabel": -1, "AltMode": -1, "epa_id": "VAD000820506"}}
]}