{"type":"FeatureCollection","features":[
{"geometry": {"type": "Point", "coordinates": [-76.4332796, 37.0735272]}, "type": "Feature", "properties": {"Status": "2", "GlobalID": "328f37d1-4c53-462c-a7aa-bcae24e9f4e6", "OBJECTID": 1, "Completed_Date": 1500940800000, "Comments": "Test", "Address": null, "Located_Date": 1500854400000}}
]}