{"type":"FeatureCollection","features":[
{"geometry": {"type": "Point", "coordinates": [-76.4332796, 37.0735272]}, "type": "Feature", "properties": {"Status": "2", "GlobalID": "50ffa75a-c3d4-4686-9529-919da38877dc", "OBJECTID": 1, "Completed_Date": 1500940800000, "Comments": "Test", "Address": null, "Located_Date": 1500854400000}}
]}